single_factor_model/__init__.py
single_factor_model/backtest.py
single_factor_model/bt_summary.py
single_factor_model/global_func.py
single_factor_model/utilise.py
single_factor_model-0.3.2.dist-info/DESCRIPTION.rst
single_factor_model-0.3.2.dist-info/METADATA
single_factor_model-0.3.2.dist-info/RECORD
single_factor_model-0.3.2.dist-info/WHEEL
single_factor_model-0.3.2.dist-info/metadata.json
single_factor_model-0.3.2.dist-info/top_level.txt
