Metadata-Version: 2.0
Name: single-factor-model
Version: 0.3.2
Summary: factor model
Home-page: UNKNOWN
Author: Yili Peng
Author-email: yili_peng@outlook.com
License: UNKNOWN
Platform: UNKNOWN
Requires-Dist: data-box
Requires-Dist: empyrical
